vvdutils
