Metadata-Version: 2.1
Name: vvdutils
Version: 0.2.4
Summary: Commonly used function library by VVD
Home-page: https://github.com/zywvvd/utils_vvd
Author: zywvvd
Author-email: zywvvd@mail.ustc.edu.cn
License: MIT
Platform: UNKNOWN
Requires-Python: >=3.14
License-File: LICENSE
